cloudshell/__init__.py
cloudshell/cp/__init__.py
cloudshell/cp/vcenter/__init__.py
cloudshell/cp/vcenter/constants.py
cloudshell/cp/vcenter/exceptions.py
cloudshell/cp/vcenter/resource_config.py
cloudshell/cp/vcenter/actions/__init__.py
cloudshell/cp/vcenter/actions/validation.py
cloudshell/cp/vcenter/actions/vm_details.py
cloudshell/cp/vcenter/actions/vm_network.py
cloudshell/cp/vcenter/common/__init__.py
cloudshell/cp/vcenter/common/vcenter/__init__.py
cloudshell/cp/vcenter/common/vcenter/data_retrieve_service.py
cloudshell/cp/vcenter/common/vcenter/event_manager.py
cloudshell/cp/vcenter/flows/__init__.py
cloudshell/cp/vcenter/flows/affinity_rules_flow.py
cloudshell/cp/vcenter/flows/autoload.py
cloudshell/cp/vcenter/flows/cluster_usage.py
cloudshell/cp/vcenter/flows/connectivity_flow.py
cloudshell/cp/vcenter/flows/customize_guest_os.py
cloudshell/cp/vcenter/flows/delete_instance.py
cloudshell/cp/vcenter/flows/get_vm_web_console.py
cloudshell/cp/vcenter/flows/power_flow.py
cloudshell/cp/vcenter/flows/reconfigure_vm.py
cloudshell/cp/vcenter/flows/refresh_ip.py
cloudshell/cp/vcenter/flows/save_restore_app.py
cloudshell/cp/vcenter/flows/snapshots.py
cloudshell/cp/vcenter/flows/validate_attributes.py
cloudshell/cp/vcenter/flows/vm_details.py
cloudshell/cp/vcenter/flows/vm_uuid_by_name.py
cloudshell/cp/vcenter/flows/deploy_vm/__init__.py
cloudshell/cp/vcenter/flows/deploy_vm/base_flow.py
cloudshell/cp/vcenter/flows/deploy_vm/from_image.py
cloudshell/cp/vcenter/flows/deploy_vm/from_linked_clone.py
cloudshell/cp/vcenter/flows/deploy_vm/from_template.py
cloudshell/cp/vcenter/flows/deploy_vm/from_vm.py
cloudshell/cp/vcenter/flows/deploy_vm/commands/__init__.py
cloudshell/cp/vcenter/flows/deploy_vm/commands/clone_vm.py
cloudshell/cp/vcenter/flows/deploy_vm/commands/create_custom_spec.py
cloudshell/cp/vcenter/flows/deploy_vm/commands/create_vm_folder.py
cloudshell/cp/vcenter/flows/deploy_vm/commands/deploy_vm_from_image.py
cloudshell_cp_vcenter-7.0.2.dist-info/METADATA
cloudshell_cp_vcenter-7.0.2.dist-info/WHEEL
cloudshell_cp_vcenter-7.0.2.dist-info/top_level.txt
cloudshell_cp_vcenter-7.0.2.dist-info/RECORD
