Metadata-Version: 2.1
Name: cloudshell-cp-vcenter
Version: 7.0.2
Summary: This Shell enables setting up vCenter as a cloud provider in CloudShell. It supports connectivity, and adds new deployment types for apps which can be used in CloudShell sandboxes.
Home-page: http://www.qualisystems.com/
Author: QualiSystems
Author-email: info@qualisystems.com
Requires-Python: ~=3.9
Requires-Dist: cloudshell-automation-api <2023.2,>=2022.1
Requires-Dist: cloudshell-shell-core ~=6.0
Requires-Dist: cloudshell-shell-standards ~=2.0
Requires-Dist: cloudshell-cp-core ~=2.5
Requires-Dist: cloudshell-logging ~=2.0
Requires-Dist: cloudshell-shell-connectivity-flow ~=4.2
Requires-Dist: requests <2.32,>=2.28
Requires-Dist: pyvmomi ~=6.7.0
Requires-Dist: jsonpickle ~=1.4
Requires-Dist: retrying ~=1.3.3
Requires-Dist: packaging <23.2,>=21.0
Requires-Dist: attrs <23.2,>=22.0
Requires-Dist: pyOpenSSL <23,>=21.0
Requires-Dist: netaddr ~=0.8
Requires-Dist: jsonschema ~=4.0
Requires-Dist: urllib3 ~=1.0
Requires-Dist: pydantic ~=2.4
Requires-Dist: typing-extensions ~=4.7
